{
  "openapi": "3.0.3",
  "info": {
    "title": "Plants Care API",
    "description": "Публичный REST API сервиса Plants Care — Telegram-бота для напоминаний об\nуходе за домашними растениями.\n\n## Аутентификация\n\nВ текущей версии (PoC, issue #85/#86) большинство пользовательских\nэндпоинтов идентифицируют вызывающего по числовому заголовку:\n\n* **`X-User-Id`** — внутренний идентификатор пользователя в БД. Используется\n  эндпоинтами `/api/v1/plants`, `/api/v1/locations`.\n* **`X-Chat-Id`** — Telegram `chat_id`. Используется эндпоинтами\n  `/api/v1/care-events`, `/api/v1/today`, `/api/v1/calendar`,\n  `/api/v1/stats/streak` и историей растения.\n\nПубличные справочники (`/api/v1/species`, `/api/v1/care-types`) аутентификацию\nне требуют.\n\n## Таймзоны и время\n\nВсе временные метки в ответах — UTC, формат `date-time` (ISO-8601).\nРасписания и расчёт «сегодня» выполняются в таймзоне конкретного\nпользователя (поле `users.timezone`), но в API наружу пробрасываются как UTC.\n\n## Ошибки\n\nВсе ошибки имеют единый формат — обёртку `{ \"error\": { code, message, details? } }`,\nсм. схему [`ApiErrorResponse`](#/components/schemas/ApiErrorResponse).\n",
    "version": "0.1.0",
    "contact": {
      "name": "Plants Care Bot",
      "url": "https://github.com/kupreichik/plants-care"
    },
    "license": {
      "name": "MIT"
    }
  },
  "servers": [
    {
      "url": "http://localhost:8080",
      "description": "Локальная разработка"
    },
    {
      "url": "https://plants-care.up.railway.app",
      "description": "Production (Railway)"
    }
  ],
  "tags": [
    {
      "name": "Health",
      "description": "Liveness probe — простой пинг для оркестратора (Railway, Docker), не проверяет состояние БД и внешних API."
    },
    {
      "name": "Plants",
      "description": "CRUD растений, принадлежащих авторизованному пользователю. Удаление —\nsoft-delete (флаг `archivedAt`), физически записи в БД остаются.\n"
    },
    {
      "name": "Plant History",
      "description": "История событий ухода для конкретного растения с пагинацией."
    },
    {
      "name": "Locations",
      "description": "Локации (комнаты/места) пользователя, в которых стоят растения. Каждый\nпользователь имеет «дефолтную» локацию, создаваемую автоматически.\n"
    },
    {
      "name": "Care Events",
      "description": "Регистрация выполнения ухода (полив, опрыскивание, удобрение) и его отмена.\nПоддерживается идемпотентность по `clientId`.\n"
    },
    {
      "name": "Calendar",
      "description": "Календарь будущих задач ухода для пользователя. Проекция активных\nрасписаний на диапазон дат (до 60 дней) в таймзоне пользователя.\n"
    },
    {
      "name": "Today",
      "description": "Задачи ухода, дедлайн которых до конца сегодняшнего дня в таймзоне пользователя."
    },
    {
      "name": "Stats",
      "description": "Статистика по уходу. Сейчас доступен только стрик растения."
    },
    {
      "name": "Species",
      "description": "Публичный справочник видов растений. Без авторизации."
    },
    {
      "name": "Care Types",
      "description": "Публичный справочник типов ухода (полив, опрыскивание, и т.п.). Без авторизации."
    }
  ],
  "paths": {
    "/api/v1/health": {
      "get": {
        "tags": [
          "Health"
        ],
        "operationId": "getHealth",
        "summary": "Liveness probe",
        "description": "Возвращает фиксированный `{\"status\":\"UP\"}` без обращения к БД или\nвнешним сервисам. Подходит как `livenessProbe` в Kubernetes/Railway.\n\nНе требует никаких заголовков и аутентификации.\n",
        "responses": {
          "200": {
            "description": "Сервис жив.",
            "content": {
              "application/json": {
                "schema": {
                  "$ref": "#/components/schemas/HealthResponse"
                },
                "example": {
                  "status": "UP"
                }
              }
            }
          }
        }
      }
    },
    "/api/v1/plants": {
      "get": {
        "tags": [
          "Plants"
        ],
        "operationId": "listPlants",
        "summary": "Список растений пользователя",
        "description": "Возвращает страницу растений, принадлежащих пользователю из заголовка\n`X-User-Id`. Архивированные (soft-deleted) растения в выдачу не\nпопадают.\n\nМожно фильтровать по локации параметром `locationId`. Пагинация —\nклассическая `offset/limit`.\n\nПараметры приводятся к безопасным границам:\n* `limit` обрезается до диапазона **[1, 100]** (всё, что больше 100,\n  становится 100; всё, что меньше 1 — становится 1);\n* `offset` ниже нуля становится 0.\n",
        "parameters": [
          {
            "$ref": "#/components/parameters/XUserId"
          },
          {
            "name": "locationId",
            "in": "query",
            "required": false,
            "description": "Идентификатор локации. Если задан, возвращаются только растения из неё.",
            "schema": {
              "type": "integer",
              "format": "int64",
              "example": 2
            }
          },
          {
            "name": "offset",
            "in": "query",
            "required": false,
            "description": "Сдвиг от начала выборки. Значения < 0 трактуются как 0.",
            "schema": {
              "type": "integer",
              "format": "int32",
              "default": 0,
              "minimum": 0,
              "example": 0
            }
          },
          {
            "name": "limit",
            "in": "query",
            "required": false,
            "description": "Размер страницы. Обрезается до [1, 100] на сервере.",
            "schema": {
              "type": "integer",
              "format": "int32",
              "default": 20,
              "minimum": 1,
              "maximum": 100,
              "example": 20
            }
          }
        ],
        "responses": {
          "200": {
            "description": "Страница растений.",
            "content": {
              "application/json": {
                "schema": {
                  "$ref": "#/components/schemas/PageResponsePlantDto"
                }
              }
            }
          },
          "400": {
            "$ref": "#/components/responses/BadRequest"
          }
        }
      },
      "post": {
        "tags": [
          "Plants"
        ],
        "operationId": "createPlant",
        "summary": "Создать растение",
        "description": "Создаёт растение от имени пользователя из `X-User-Id`. Если\n`locationId` не указан, растение попадает в дефолтную локацию\nпользователя.\n",
        "parameters": [
          {
            "$ref": "#/components/parameters/XUserId"
          }
        ],
        "requestBody": {
          "required": true,
          "content": {
            "application/json": {
              "schema": {
                "$ref": "#/components/schemas/PlantCreateRequest"
              },
              "example": {
                "name": "Monstera",
                "notes": "Стоит у окна, любит свет",
                "locationId": 2
              }
            }
          }
        },
        "responses": {
          "201": {
            "description": "Растение создано.",
            "content": {
              "application/json": {
                "schema": {
                  "$ref": "#/components/schemas/PlantDto"
                }
              }
            }
          },
          "400": {
            "$ref": "#/components/responses/BadRequest"
          }
        }
      }
    },
    "/api/v1/plants/{id}": {
      "get": {
        "tags": [
          "Plants"
        ],
        "operationId": "getPlant",
        "summary": "Получить растение по ID",
        "description": "Возвращает растение, если оно принадлежит пользователю из `X-User-Id`\nи не архивировано. Чужие или несуществующие растения отдаются как 404,\nчужие активные — как 403 (когда сервис уже знает, что запись есть, но\nпринадлежит другому пользователю).\n",
        "parameters": [
          {
            "$ref": "#/components/parameters/XUserId"
          },
          {
            "$ref": "#/components/parameters/PlantIdPath"
          }
        ],
        "responses": {
          "200": {
            "description": "Растение найдено.",
            "content": {
              "application/json": {
                "schema": {
                  "$ref": "#/components/schemas/PlantDto"
                }
              }
            }
          },
          "403": {
            "$ref": "#/components/responses/Forbidden"
          },
          "404": {
            "$ref": "#/components/responses/NotFound"
          }
        }
      },
      "put": {
        "tags": [
          "Plants"
        ],
        "operationId": "updatePlant",
        "summary": "Обновить растение (PATCH-семантика)",
        "description": "Несмотря на HTTP-метод `PUT`, апдейт реализован по принципу PATCH:\nобновляются **только присутствующие в теле** поля. Передача `null`\nв поле трактуется как «не менять».\n\nПример: чтобы переместить растение в другую локацию, достаточно\nотправить `{ \"locationId\": 5 }`.\n",
        "parameters": [
          {
            "$ref": "#/components/parameters/XUserId"
          },
          {
            "$ref": "#/components/parameters/PlantIdPath"
          }
        ],
        "requestBody": {
          "required": true,
          "content": {
            "application/json": {
              "schema": {
                "$ref": "#/components/schemas/PlantUpdateRequest"
              },
              "example": {
                "name": "Monstera deliciosa",
                "notes": "Поливать раз в неделю"
              }
            }
          }
        },
        "responses": {
          "200": {
            "description": "Растение обновлено.",
            "content": {
              "application/json": {
                "schema": {
                  "$ref": "#/components/schemas/PlantDto"
                }
              }
            }
          },
          "400": {
            "$ref": "#/components/responses/BadRequest"
          },
          "403": {
            "$ref": "#/components/responses/Forbidden"
          },
          "404": {
            "$ref": "#/components/responses/NotFound"
          }
        }
      },
      "delete": {
        "tags": [
          "Plants"
        ],
        "operationId": "deletePlant",
        "summary": "Архивировать растение (soft-delete)",
        "description": "Помечает растение как удалённое (`archived_at = now()` в UTC). Запись\nв БД остаётся, но перестаёт появляться во всех `/api/v1/plants/*`\nвыборках. Восстановления через API в этой версии нет.\n",
        "parameters": [
          {
            "$ref": "#/components/parameters/XUserId"
          },
          {
            "$ref": "#/components/parameters/PlantIdPath"
          }
        ],
        "responses": {
          "204": {
            "description": "Растение архивировано. Тело ответа отсутствует."
          },
          "403": {
            "$ref": "#/components/responses/Forbidden"
          },
          "404": {
            "$ref": "#/components/responses/NotFound"
          }
        }
      }
    },
    "/api/v1/plants/{id}/history": {
      "get": {
        "tags": [
          "Plant History"
        ],
        "operationId": "getPlantHistory",
        "summary": "История событий ухода за растением",
        "description": "Возвращает страницу истории ухода за растением, принадлежащим\nпользователю из заголовка `X-Chat-Id` (Telegram chat_id).\n\nВ выдачу попадают только активные (не отменённые) записи всех типов\nухода **кроме `SOIL_CHECK`** — это служебный тип, который наружу не\nвыставляется.\n\nПагинация — `limit/offset`. `limit` строго в диапазоне [1, 100]\n(значения вне диапазона отдаются как 400). `offset` < 0 нормализуется\nв 0.\n",
        "parameters": [
          {
            "$ref": "#/components/parameters/XChatId"
          },
          {
            "$ref": "#/components/parameters/PlantIdPath"
          },
          {
            "name": "limit",
            "in": "query",
            "required": false,
            "description": "Размер страницы. Допустимые значения — [1, 100].",
            "schema": {
              "type": "integer",
              "format": "int32",
              "default": 20,
              "minimum": 1,
              "maximum": 100
            }
          },
          {
            "name": "offset",
            "in": "query",
            "required": false,
            "description": "Сдвиг от начала истории. Значения < 0 нормализуются в 0.",
            "schema": {
              "type": "integer",
              "format": "int32",
              "default": 0,
              "minimum": 0
            }
          }
        ],
        "responses": {
          "200": {
            "description": "Страница истории.",
            "content": {
              "application/json": {
                "schema": {
                  "$ref": "#/components/schemas/PlantHistoryResponse"
                }
              }
            }
          },
          "400": {
            "$ref": "#/components/responses/BadRequest"
          },
          "404": {
            "$ref": "#/components/responses/NotFound"
          }
        }
      }
    },
    "/api/v1/locations": {
      "get": {
        "tags": [
          "Locations"
        ],
        "operationId": "listLocations",
        "summary": "Список локаций пользователя",
        "description": "Возвращает все локации, принадлежащие пользователю из `X-User-Id`.\nБез пагинации — у пользователя обычно меньше десятка локаций.\n",
        "parameters": [
          {
            "$ref": "#/components/parameters/XUserId"
          }
        ],
        "responses": {
          "200": {
            "description": "Список локаций.",
            "content": {
              "application/json": {
                "schema": {
                  "type": "array",
                  "items": {
                    "$ref": "#/components/schemas/LocationDto"
                  }
                }
              }
            }
          }
        }
      },
      "post": {
        "tags": [
          "Locations"
        ],
        "operationId": "createLocation",
        "summary": "Создать локацию",
        "description": "Создаёт локацию от имени пользователя. Имя уникально в рамках\nпользователя — при коллизии возвращается 400 с `code=BAD_REQUEST`.\n",
        "parameters": [
          {
            "$ref": "#/components/parameters/XUserId"
          }
        ],
        "requestBody": {
          "required": true,
          "content": {
            "application/json": {
              "schema": {
                "$ref": "#/components/schemas/LocationCreateRequest"
              },
              "example": {
                "name": "Подоконник",
                "emoji": "🪟"
              }
            }
          }
        },
        "responses": {
          "201": {
            "description": "Локация создана.",
            "content": {
              "application/json": {
                "schema": {
                  "$ref": "#/components/schemas/LocationDto"
                }
              }
            }
          },
          "400": {
            "$ref": "#/components/responses/BadRequest"
          }
        }
      }
    },
    "/api/v1/locations/{id}": {
      "get": {
        "tags": [
          "Locations"
        ],
        "operationId": "getLocation",
        "summary": "Получить локацию по ID",
        "description": "Возвращает локацию, если она принадлежит пользователю. Чужие или\nнесуществующие локации — 404 (различения не делаем, чтобы не\nраскрывать существование чужих ID).\n",
        "parameters": [
          {
            "$ref": "#/components/parameters/XUserId"
          },
          {
            "$ref": "#/components/parameters/LocationIdPath"
          }
        ],
        "responses": {
          "200": {
            "description": "Локация найдена.",
            "content": {
              "application/json": {
                "schema": {
                  "$ref": "#/components/schemas/LocationDto"
                }
              }
            }
          },
          "404": {
            "$ref": "#/components/responses/NotFound"
          }
        }
      },
      "put": {
        "tags": [
          "Locations"
        ],
        "operationId": "updateLocation",
        "summary": "Обновить локацию",
        "description": "PATCH-семантика — обновляются только переданные поля.",
        "parameters": [
          {
            "$ref": "#/components/parameters/XUserId"
          },
          {
            "$ref": "#/components/parameters/LocationIdPath"
          }
        ],
        "requestBody": {
          "required": true,
          "content": {
            "application/json": {
              "schema": {
                "$ref": "#/components/schemas/LocationUpdateRequest"
              }
            }
          }
        },
        "responses": {
          "200": {
            "description": "Локация обновлена.",
            "content": {
              "application/json": {
                "schema": {
                  "$ref": "#/components/schemas/LocationDto"
                }
              }
            }
          },
          "400": {
            "$ref": "#/components/responses/BadRequest"
          },
          "404": {
            "$ref": "#/components/responses/NotFound"
          }
        }
      },
      "delete": {
        "tags": [
          "Locations"
        ],
        "operationId": "deleteLocation",
        "summary": "Удалить локацию",
        "description": "Удаляет локацию. Если в локации есть растения — обязательно передать\n`targetLocationId`, чтобы переместить их в другую локацию того же\nпользователя.\n\nЕсли растений нет — `targetLocationId` игнорируется.\n\nОсобый код ошибки `LOCATION_NOT_EMPTY` возвращается, когда в локации\nесть растения, а `targetLocationId` не задан.\n",
        "parameters": [
          {
            "$ref": "#/components/parameters/XUserId"
          },
          {
            "$ref": "#/components/parameters/LocationIdPath"
          },
          {
            "name": "targetLocationId",
            "in": "query",
            "required": false,
            "description": "Локация, куда переместить растения. Обязателен, если в удаляемой локации есть растения.",
            "schema": {
              "type": "integer",
              "format": "int64",
              "example": 2
            }
          }
        ],
        "responses": {
          "204": {
            "description": "Локация удалена."
          },
          "400": {
            "description": "Невалидный запрос или попытка удалить непустую локацию без\n`targetLocationId`. В последнем случае `code=LOCATION_NOT_EMPTY`.\n",
            "content": {
              "application/json": {
                "schema": {
                  "$ref": "#/components/schemas/ApiErrorResponse"
                },
                "examples": {
                  "notEmpty": {
                    "summary": "Локация содержит растения",
                    "value": {
                      "error": {
                        "code": "LOCATION_NOT_EMPTY",
                        "message": "Provide targetLocationId to move plants"
                      }
                    }
                  }
                }
              }
            }
          },
          "404": {
            "$ref": "#/components/responses/NotFound"
          }
        }
      }
    },
    "/api/v1/care-events": {
      "post": {
        "tags": [
          "Care Events"
        ],
        "operationId": "createCareEvent",
        "summary": "Зарегистрировать событие ухода",
        "description": "Записывает выполнение ухода (полив/опрыскивание/удобрение) для растения\nпользователя. После записи пересчитывается ближайший дедлайн в\nсвязанном расписании.\n\n## Идемпотентность\n\nЕсли в теле передан `clientId`, и ранее уже была зарегистрирована\nзапись с таким `clientId` от того же пользователя/растения, возвращается\nсуществующая запись без повторной вставки. Это позволяет мобильным\nклиентам безопасно ретраить запрос при потере соединения.\n",
        "parameters": [
          {
            "$ref": "#/components/parameters/XChatId"
          }
        ],
        "requestBody": {
          "required": true,
          "content": {
            "application/json": {
              "schema": {
                "$ref": "#/components/schemas/CreateCareEventRequest"
              },
              "example": {
                "plantId": 10,
                "type": "WATER",
                "performedAt": "2026-05-22T10:00:00Z",
                "note": "Полил из лейки, грунт был сухой",
                "clientId": "9b1c4a36-3f6f-4a92-8b69-fb1d2cb1d2a1"
              }
            }
          }
        },
        "responses": {
          "201": {
            "description": "Событие зарегистрировано (или возвращена существующая запись с тем же `clientId`).",
            "content": {
              "application/json": {
                "schema": {
                  "$ref": "#/components/schemas/CareEventResponse"
                }
              }
            }
          },
          "400": {
            "$ref": "#/components/responses/BadRequest"
          },
          "404": {
            "$ref": "#/components/responses/NotFound"
          }
        }
      }
    },
    "/api/v1/care-events/{id}": {
      "delete": {
        "tags": [
          "Care Events"
        ],
        "operationId": "cancelCareEvent",
        "summary": "Отменить событие ухода (компенсация)",
        "description": "Запись физически не удаляется — создаётся компенсирующая запись и в\nисходной проставляется FK `cancelled_by`. Это сохраняет полную историю\nи позволяет восстанавливать состояние.\n\nПовторная отмена уже отменённой записи возвращает 409.\n",
        "parameters": [
          {
            "$ref": "#/components/parameters/XChatId"
          },
          {
            "name": "id",
            "in": "path",
            "required": true,
            "description": "Идентификатор записи `care_history`.",
            "schema": {
              "type": "integer",
              "format": "int64",
              "example": 5
            }
          }
        ],
        "responses": {
          "204": {
            "description": "Событие отменено."
          },
          "404": {
            "$ref": "#/components/responses/NotFound"
          },
          "409": {
            "$ref": "#/components/responses/Conflict"
          }
        }
      }
    },
    "/api/v1/calendar": {
      "get": {
        "tags": [
          "Calendar"
        ],
        "operationId": "getCalendar",
        "summary": "Календарь задач ухода на диапазон дат",
        "description": "Возвращает проекцию активных расписаний пользователя на диапазон дат\n`[from, to]` (включительно), сгруппированную по дате.\n\nДни без задач в ответе **не появляются**. Ключи объекта-результата —\nстроки-даты в формате `YYYY-MM-DD`, упорядоченные по возрастанию.\n\nМаксимальная длина диапазона — 60 дней; больше → 400.\n",
        "parameters": [
          {
            "$ref": "#/components/parameters/XChatId"
          },
          {
            "name": "from",
            "in": "query",
            "required": true,
            "description": "Начало диапазона (включительно).",
            "schema": {
              "type": "string",
              "format": "date",
              "example": "2026-05-24"
            }
          },
          {
            "name": "to",
            "in": "query",
            "required": true,
            "description": "Конец диапазона (включительно). Разница `to - from` ≤ 60 дней.",
            "schema": {
              "type": "string",
              "format": "date",
              "example": "2026-06-22"
            }
          }
        ],
        "responses": {
          "200": {
            "description": "Карта «дата → задачи».",
            "content": {
              "application/json": {
                "schema": {
                  "$ref": "#/components/schemas/CalendarResponse"
                }
              }
            }
          },
          "400": {
            "$ref": "#/components/responses/BadRequest"
          }
        }
      }
    },
    "/api/v1/today": {
      "get": {
        "tags": [
          "Today"
        ],
        "operationId": "getToday",
        "summary": "Задачи на сегодня",
        "description": "Возвращает задачи ухода, дедлайн которых наступает до конца\nсегодняшнего дня в **таймзоне пользователя** (`users.timezone`).\n\nУчитываются только активные расписания; завершённые или приостановленные\nне попадают в выдачу.\n",
        "parameters": [
          {
            "$ref": "#/components/parameters/XChatId"
          }
        ],
        "responses": {
          "200": {
            "description": "Список задач на сегодня.",
            "content": {
              "application/json": {
                "schema": {
                  "$ref": "#/components/schemas/TodayResponse"
                }
              }
            }
          }
        }
      }
    },
    "/api/v1/stats/streak": {
      "get": {
        "tags": [
          "Stats"
        ],
        "operationId": "getPlantStreak",
        "summary": "Текущий стрик растения",
        "description": "Возвращает текущий «стрик» растения — количество последовательных\nвыполнений ухода без пропусков (`on_time = true` подряд).\n\nПроверяется владение растением: если растение принадлежит другому\nпользователю или не существует — 404.\n",
        "parameters": [
          {
            "$ref": "#/components/parameters/XChatId"
          },
          {
            "name": "plantId",
            "in": "query",
            "required": true,
            "description": "Идентификатор растения, для которого считаем стрик.",
            "schema": {
              "type": "integer",
              "format": "int64",
              "example": 10
            }
          }
        ],
        "responses": {
          "200": {
            "description": "Стрик посчитан.",
            "content": {
              "application/json": {
                "schema": {
                  "$ref": "#/components/schemas/StreakResponse"
                }
              }
            }
          },
          "404": {
            "$ref": "#/components/responses/NotFound"
          }
        }
      }
    },
    "/api/v1/species": {
      "get": {
        "tags": [
          "Species"
        ],
        "operationId": "listSpecies",
        "summary": "Поиск/список видов растений",
        "description": "Публичный справочник видов. Без авторизации. Кеширован на стороне\nсервера (TTL 1 час) для популярных запросов.\n\nПараметр `q` — необязательный поиск по подстроке имени/латинского имени.\nЕсли пустой — возвращаются все виды постранично.\n\nПагинация в этой версии переведена с `page/size` на унифицированный\n`offset/limit` (как в остальных списках API). Внутри сервиса\nконвертируется в `PageRequest.of(offset/limit, limit)`, поэтому\n`offset` должен быть кратен `limit` для предсказуемой страницы.\n\n`limit` обрезается до 100.\n",
        "parameters": [
          {
            "name": "q",
            "in": "query",
            "required": false,
            "description": "Подстрока для поиска по имени или латинскому имени. Если пустая — без фильтра.",
            "schema": {
              "type": "string",
              "default": "",
              "example": "монстера"
            }
          },
          {
            "name": "offset",
            "in": "query",
            "required": false,
            "description": "Сдвиг от начала.",
            "schema": {
              "type": "integer",
              "format": "int32",
              "default": 0,
              "minimum": 0
            }
          },
          {
            "name": "limit",
            "in": "query",
            "required": false,
            "description": "Размер страницы. Обрезается до 100.",
            "schema": {
              "type": "integer",
              "format": "int32",
              "default": 20,
              "minimum": 1,
              "maximum": 100
            }
          }
        ],
        "responses": {
          "200": {
            "description": "Страница видов.",
            "content": {
              "application/json": {
                "schema": {
                  "$ref": "#/components/schemas/PageResponseSpeciesSummaryDto"
                }
              }
            }
          }
        }
      }
    },
    "/api/v1/species/{id}": {
      "get": {
        "tags": [
          "Species"
        ],
        "operationId": "getSpecies",
        "summary": "Детали вида растения",
        "description": "Полная карточка вида, включая `description`. Кешируется по `id`\n(TTL 1 час).\n",
        "parameters": [
          {
            "name": "id",
            "in": "path",
            "required": true,
            "description": "Идентификатор вида.",
            "schema": {
              "type": "integer",
              "format": "int64",
              "example": 5
            }
          }
        ],
        "responses": {
          "200": {
            "description": "Вид найден.",
            "content": {
              "application/json": {
                "schema": {
                  "$ref": "#/components/schemas/SpeciesDetailDto"
                }
              }
            }
          },
          "404": {
            "$ref": "#/components/responses/NotFound"
          }
        }
      }
    },
    "/api/v1/care-types": {
      "get": {
        "tags": [
          "Care Types"
        ],
        "operationId": "listCareTypes",
        "summary": "Справочник типов ухода",
        "description": "Возвращает все типы ухода с локализованными русскими названиями.\nСписок фиксирован: `WATERING`, `MISTING`, `FERTILIZING`, `SOIL_CHECK`.\n\nАутентификация не требуется.\n",
        "responses": {
          "200": {
            "description": "Список типов ухода.",
            "content": {
              "application/json": {
                "schema": {
                  "type": "array",
                  "items": {
                    "$ref": "#/components/schemas/CareTypeDto"
                  }
                }
              }
            }
          }
        }
      }
    }
  },
  "components": {
    "parameters": {
      "XUserId": {
        "name": "X-User-Id",
        "in": "header",
        "required": true,
        "description": "Внутренний идентификатор пользователя (поле `users.id` в БД). Временный\nспособ идентификации до появления настоящей авторизации.\n",
        "schema": {
          "type": "integer",
          "format": "int64",
          "example": 1
        }
      },
      "XChatId": {
        "name": "X-Chat-Id",
        "in": "header",
        "required": true,
        "description": "Telegram `chat_id` авторизованного пользователя. Резолвится в `users.id`\nна стороне сервера через `UserApiResolver`.\n",
        "schema": {
          "type": "integer",
          "format": "int64",
          "example": 9000001
        }
      },
      "PlantIdPath": {
        "name": "id",
        "in": "path",
        "required": true,
        "description": "Идентификатор растения.",
        "schema": {
          "type": "integer",
          "format": "int64",
          "example": 1
        }
      },
      "LocationIdPath": {
        "name": "id",
        "in": "path",
        "required": true,
        "description": "Идентификатор локации.",
        "schema": {
          "type": "integer",
          "format": "int64",
          "example": 1
        }
      }
    },
    "responses": {
      "BadRequest": {
        "description": "Невалидный запрос. Возвращается при провале Bean Validation\n(`VALIDATION_ERROR` + `details` по полям) или при неприемлемых\nпараметрах (`BAD_REQUEST`).\n",
        "content": {
          "application/json": {
            "schema": {
              "$ref": "#/components/schemas/ApiErrorResponse"
            },
            "examples": {
              "validation": {
                "summary": "Ошибка валидации поля",
                "value": {
                  "error": {
                    "code": "VALIDATION_ERROR",
                    "message": "Validation failed",
                    "details": [
                      {
                        "field": "name",
                        "message": "must not be blank"
                      }
                    ]
                  }
                }
              },
              "badRequest": {
                "summary": "Невалидный аргумент",
                "value": {
                  "error": {
                    "code": "BAD_REQUEST",
                    "message": "limit must be between 1 and 100"
                  }
                }
              }
            }
          }
        }
      },
      "Forbidden": {
        "description": "Ресурс существует, но принадлежит другому пользователю.",
        "content": {
          "application/json": {
            "schema": {
              "$ref": "#/components/schemas/ApiErrorResponse"
            },
            "example": {
              "error": {
                "code": "ACCESS_DENIED",
                "message": "Access denied"
              }
            }
          }
        }
      },
      "NotFound": {
        "description": "Ресурс не найден или архивирован.",
        "content": {
          "application/json": {
            "schema": {
              "$ref": "#/components/schemas/ApiErrorResponse"
            },
            "example": {
              "error": {
                "code": "NOT_FOUND",
                "message": "Resource not found"
              }
            }
          }
        }
      },
      "Conflict": {
        "description": "Конфликт состояния — например, попытка нарушить инвариант домена.",
        "content": {
          "application/json": {
            "schema": {
              "$ref": "#/components/schemas/ApiErrorResponse"
            },
            "example": {
              "error": {
                "code": "CONFLICT",
                "message": "Operation not allowed in the current state"
              }
            }
          }
        }
      }
    },
    "schemas": {
      "LocationDto": {
        "type": "object",
        "description": "Локация (комната/место), в которой пользователь держит растения.",
        "required": [
          "id",
          "name",
          "defaultLocation"
        ],
        "properties": {
          "id": {
            "type": "integer",
            "format": "int64"
          },
          "name": {
            "type": "string",
            "example": "Подоконник"
          },
          "emoji": {
            "type": "string",
            "nullable": true,
            "example": "🪟"
          },
          "defaultLocation": {
            "type": "boolean",
            "description": "Является ли локация дефолтной для пользователя.",
            "example": false
          },
          "createdAt": {
            "type": "string",
            "format": "date-time",
            "nullable": true
          }
        }
      },
      "LocationCreateRequest": {
        "type": "object",
        "required": [
          "name"
        ],
        "properties": {
          "name": {
            "type": "string",
            "minLength": 1,
            "maxLength": 30,
            "example": "Подоконник"
          },
          "emoji": {
            "type": "string",
            "maxLength": 16,
            "nullable": true,
            "example": "🌿"
          }
        }
      },
      "LocationUpdateRequest": {
        "type": "object",
        "description": "Все поля опциональны.",
        "properties": {
          "name": {
            "type": "string",
            "minLength": 1,
            "maxLength": 30,
            "nullable": true
          },
          "emoji": {
            "type": "string",
            "maxLength": 16,
            "nullable": true
          }
        }
      },
      "PlantDto": {
        "type": "object",
        "description": "Растение в формате REST API. Поля `locationName` / `speciesName`\nденормализованы из связанных сущностей для удобства фронта.\n",
        "required": [
          "id",
          "name",
          "archived"
        ],
        "properties": {
          "id": {
            "type": "integer",
            "format": "int64",
            "description": "Уникальный идентификатор растения.",
            "example": 1
          },
          "name": {
            "type": "string",
            "description": "Имя растения, заданное пользователем.",
            "example": "Monstera"
          },
          "notes": {
            "type": "string",
            "nullable": true,
            "description": "Произвольные заметки пользователя.",
            "example": "Стоит у окна, любит свет"
          },
          "photoFileId": {
            "type": "string",
            "nullable": true,
            "description": "Telegram `file_id` загруженной фотографии. Используется ботом для повторной отправки без скачивания."
          },
          "locationId": {
            "type": "integer",
            "format": "int64",
            "nullable": true,
            "description": "Идентификатор локации, в которой стоит растение.",
            "example": 2
          },
          "locationName": {
            "type": "string",
            "nullable": true,
            "description": "Денормализованное имя локации на момент запроса.",
            "example": "Подоконник"
          },
          "speciesId": {
            "type": "integer",
            "format": "int64",
            "nullable": true,
            "description": "Идентификатор вида из справочника.",
            "example": 5
          },
          "speciesName": {
            "type": "string",
            "nullable": true,
            "description": "Денормализованное название вида.",
            "example": "Monstera deliciosa"
          },
          "archived": {
            "type": "boolean",
            "description": "Признак того, что растение архивировано (soft-deleted). В выдаче списков всегда `false`.",
            "example": false
          },
          "createdAt": {
            "type": "string",
            "format": "date-time",
            "nullable": true,
            "description": "Момент создания записи в БД (UTC).",
            "example": "2026-05-24T10:15:30Z"
          }
        }
      },
      "PlantCreateRequest": {
        "type": "object",
        "description": "Тело POST /api/v1/plants.",
        "required": [
          "name"
        ],
        "properties": {
          "name": {
            "type": "string",
            "minLength": 1,
            "maxLength": 100,
            "description": "Имя нового растения. Обязательно, не пустое.",
            "example": "Monstera"
          },
          "notes": {
            "type": "string",
            "maxLength": 2000,
            "nullable": true,
            "description": "Опциональные заметки пользователя."
          },
          "locationId": {
            "type": "integer",
            "format": "int64",
            "nullable": true,
            "description": "Идентификатор локации. Если не задан, используется дефолтная локация пользователя."
          }
        }
      },
      "PlantUpdateRequest": {
        "type": "object",
        "description": "Тело PUT /api/v1/plants/{id}. Все поля опциональны.",
        "properties": {
          "name": {
            "type": "string",
            "minLength": 1,
            "maxLength": 100,
            "nullable": true
          },
          "notes": {
            "type": "string",
            "maxLength": 2000,
            "nullable": true
          },
          "locationId": {
            "type": "integer",
            "format": "int64",
            "nullable": true
          }
        }
      },
      "PageResponsePlantDto": {
        "type": "object",
        "description": "Постраничный ответ со списком растений.",
        "required": [
          "items",
          "total",
          "offset",
          "limit"
        ],
        "properties": {
          "items": {
            "type": "array",
            "description": "Растения на текущей странице.",
            "items": {
              "$ref": "#/components/schemas/PlantDto"
            }
          },
          "total": {
            "type": "integer",
            "format": "int32",
            "description": "Общее количество растений, удовлетворяющих фильтру.",
            "example": 42
          },
          "offset": {
            "type": "integer",
            "format": "int32",
            "example": 0
          },
          "limit": {
            "type": "integer",
            "format": "int32",
            "example": 20
          }
        }
      },
      "SpeciesSummaryDto": {
        "type": "object",
        "description": "Краткая карточка вида для списка.",
        "required": [
          "id",
          "name"
        ],
        "properties": {
          "id": {
            "type": "integer",
            "format": "int64"
          },
          "name": {
            "type": "string",
            "example": "Монстера"
          },
          "latinName": {
            "type": "string",
            "nullable": true,
            "example": "Monstera deliciosa"
          },
          "wateringDays": {
            "type": "integer",
            "format": "int32",
            "nullable": true,
            "description": "Рекомендуемый интервал полива в днях."
          },
          "mistingDays": {
            "type": "integer",
            "format": "int32",
            "nullable": true
          },
          "fertilizingDays": {
            "type": "integer",
            "format": "int32",
            "nullable": true
          },
          "soilCheckDays": {
            "type": "integer",
            "format": "int32",
            "nullable": true
          },
          "careDifficulty": {
            "type": "string",
            "nullable": true,
            "description": "Имя enum'а `CareDifficulty.name()`.",
            "example": "EASY"
          },
          "lightPreference": {
            "type": "string",
            "nullable": true,
            "description": "Имя enum'а `LightPreference.name()`.",
            "example": "BRIGHT_INDIRECT"
          }
        }
      },
      "SpeciesDetailDto": {
        "type": "object",
        "description": "Полная карточка вида. Все поля `SpeciesSummaryDto` плюс `description`.\n",
        "required": [
          "id",
          "name"
        ],
        "properties": {
          "id": {
            "type": "integer",
            "format": "int64"
          },
          "name": {
            "type": "string"
          },
          "latinName": {
            "type": "string",
            "nullable": true
          },
          "wateringDays": {
            "type": "integer",
            "format": "int32",
            "nullable": true
          },
          "mistingDays": {
            "type": "integer",
            "format": "int32",
            "nullable": true
          },
          "fertilizingDays": {
            "type": "integer",
            "format": "int32",
            "nullable": true
          },
          "soilCheckDays": {
            "type": "integer",
            "format": "int32",
            "nullable": true
          },
          "careDifficulty": {
            "type": "string",
            "nullable": true
          },
          "lightPreference": {
            "type": "string",
            "nullable": true
          },
          "description": {
            "type": "string",
            "nullable": true,
            "description": "Длинное текстовое описание вида."
          }
        }
      },
      "PageResponseSpeciesSummaryDto": {
        "type": "object",
        "description": "Постраничный ответ со списком видов. Унифицирован под `{items, total,\noffset, limit}` — отличается от прошлой реализации, где было\n`{content, page, size, totalElements, totalPages}`. Это **breaking\nchange** для существующих клиентов `/api/v1/species`.\n",
        "required": [
          "items",
          "total",
          "offset",
          "limit"
        ],
        "properties": {
          "items": {
            "type": "array",
            "items": {
              "$ref": "#/components/schemas/SpeciesSummaryDto"
            }
          },
          "total": {
            "type": "integer",
            "format": "int64",
            "description": "Общее количество видов (с учётом фильтра `q`)."
          },
          "offset": {
            "type": "integer",
            "format": "int32"
          },
          "limit": {
            "type": "integer",
            "format": "int32"
          }
        }
      },
      "TodayResponse": {
        "type": "object",
        "description": "Ответ `GET /api/v1/today`.",
        "required": [
          "tasks",
          "count"
        ],
        "properties": {
          "tasks": {
            "type": "array",
            "items": {
              "$ref": "#/components/schemas/TaskDto"
            }
          },
          "count": {
            "type": "integer",
            "format": "int32",
            "description": "Длина `tasks` (дублируется для удобства клиента)."
          }
        }
      },
      "HealthResponse": {
        "type": "object",
        "description": "Ответ liveness-эндпоинта.",
        "required": [
          "status"
        ],
        "properties": {
          "status": {
            "type": "string",
            "description": "Фиксированное значение `UP`, когда приложение принимает HTTP-запросы.",
            "example": "UP"
          }
        }
      },
      "CareTypeDto": {
        "type": "object",
        "description": "Локализованная карточка типа ухода.",
        "required": [
          "code",
          "displayName"
        ],
        "properties": {
          "code": {
            "type": "string",
            "description": "Машинное имя `TaskType.name()`.",
            "enum": [
              "WATERING",
              "MISTING",
              "FERTILIZING",
              "SOIL_CHECK"
            ],
            "example": "WATERING"
          },
          "displayName": {
            "type": "string",
            "description": "Локализованное русское имя для UI.",
            "example": "Полив"
          }
        }
      },
      "CareEventType": {
        "type": "string",
        "description": "Публичный тип ухода. **Намеренно не совпадает** один-к-одному с\nвнутренним `TaskType`: API-контракт стабилен и не зависит от\nэволюции доменной модели. Тип `SOIL_CHECK` через REST не доступен.\n",
        "enum": [
          "WATER",
          "SPRAY",
          "FERTILIZE"
        ],
        "example": "WATER"
      },
      "CreateCareEventRequest": {
        "type": "object",
        "description": "Тело POST /api/v1/care-events.",
        "required": [
          "plantId",
          "type",
          "performedAt"
        ],
        "properties": {
          "plantId": {
            "type": "integer",
            "format": "int64",
            "example": 10
          },
          "type": {
            "$ref": "#/components/schemas/CareEventType"
          },
          "performedAt": {
            "type": "string",
            "format": "date-time",
            "description": "Момент выполнения ухода (UTC).",
            "example": "2026-05-22T10:00:00Z"
          },
          "note": {
            "type": "string",
            "nullable": true,
            "description": "Необязательная заметка (например, «добавил удобрение X»)."
          },
          "clientId": {
            "type": "string",
            "nullable": true,
            "description": "UUID от клиента для идемпотентности при retry. Если null — идемпотентность отключена."
          }
        }
      },
      "CareEventResponse": {
        "type": "object",
        "description": "Запись события ухода после регистрации или из истории.",
        "required": [
          "id",
          "plantId",
          "plantName",
          "type",
          "performedAt",
          "onTime"
        ],
        "properties": {
          "id": {
            "type": "integer",
            "format": "int64"
          },
          "plantId": {
            "type": "integer",
            "format": "int64"
          },
          "plantName": {
            "type": "string"
          },
          "type": {
            "$ref": "#/components/schemas/CareEventType"
          },
          "performedAt": {
            "type": "string",
            "format": "date-time",
            "description": "Момент выполнения в UTC."
          },
          "note": {
            "type": "string",
            "nullable": true
          },
          "clientId": {
            "type": "string",
            "nullable": true
          },
          "onTime": {
            "type": "boolean",
            "description": "Признак выполнения «в срок» — выполнено до дедлайна расписания.\nИспользуется для расчёта стрика.\n"
          }
        }
      },
      "PlantHistoryResponse": {
        "type": "object",
        "description": "Страница истории ухода за растением с метаданными пагинации.",
        "required": [
          "items",
          "total",
          "limit",
          "offset"
        ],
        "properties": {
          "items": {
            "type": "array",
            "items": {
              "$ref": "#/components/schemas/CareEventResponse"
            }
          },
          "total": {
            "type": "integer",
            "format": "int64",
            "description": "Общее количество активных записей.",
            "example": 17
          },
          "limit": {
            "type": "integer",
            "format": "int32",
            "example": 20
          },
          "offset": {
            "type": "integer",
            "format": "int32",
            "example": 0
          }
        }
      },
      "StreakResponse": {
        "type": "object",
        "description": "Ответ `GET /api/v1/stats/streak`.",
        "required": [
          "plantId",
          "streak"
        ],
        "properties": {
          "plantId": {
            "type": "integer",
            "format": "int64"
          },
          "streak": {
            "type": "integer",
            "format": "int32",
            "description": "Количество on-time подряд.",
            "example": 7
          }
        }
      },
      "TaskDto": {
        "type": "object",
        "description": "Задача ухода в выдаче `today`/`calendar`.",
        "required": [
          "scheduleId",
          "plantId",
          "plantName",
          "taskType",
          "nextDueAt"
        ],
        "properties": {
          "scheduleId": {
            "type": "integer",
            "format": "int64"
          },
          "plantId": {
            "type": "integer",
            "format": "int64"
          },
          "plantName": {
            "type": "string"
          },
          "taskType": {
            "type": "string",
            "description": "Имя `TaskType.name()` — `WATERING` / `MISTING` / `FERTILIZING` / `SOIL_CHECK`.",
            "example": "WATERING"
          },
          "locationName": {
            "type": "string",
            "nullable": true
          },
          "nextDueAt": {
            "type": "string",
            "format": "date-time",
            "description": "Ближайший дедлайн (UTC)."
          }
        }
      },
      "CalendarResponse": {
        "type": "object",
        "description": "Карта `date → tasks` для эндпоинта `/api/v1/calendar`. Ключи — строки\nв формате `YYYY-MM-DD`. В JSON отсортированы по возрастанию.\n\n⚠️ Внутренний $ref на TaskDto использует bundle-путь\n`#/components/schemas/TaskDto` (а не относительный к этому файлу),\nпотому что openapi-generator 7.10 теряет типизацию items внутри\n`additionalProperties` при cross-file разрешении.\n",
        "additionalProperties": {
          "type": "array",
          "items": {
            "$ref": "#/components/schemas/TaskDto"
          }
        }
      },
      "ApiErrorResponse": {
        "type": "object",
        "description": "Стандартная обёртка над ошибкой REST API.",
        "required": [
          "error"
        ],
        "properties": {
          "error": {
            "$ref": "#/components/schemas/ApiError"
          }
        }
      },
      "ApiError": {
        "type": "object",
        "description": "Тело ошибки.",
        "required": [
          "code",
          "message"
        ],
        "properties": {
          "code": {
            "type": "string",
            "description": "Стабильный машиночитаемый код. Значения:\n`VALIDATION_ERROR`, `BAD_REQUEST`, `NOT_FOUND`, `ACCESS_DENIED`,\n`CONFLICT`, `INTERNAL_ERROR`, `LOCATION_NOT_EMPTY`.\n",
            "example": "VALIDATION_ERROR"
          },
          "message": {
            "type": "string",
            "example": "Validation failed"
          },
          "details": {
            "type": "array",
            "nullable": true,
            "description": "Список ошибок по полям. Заполняется только для `VALIDATION_ERROR`.",
            "items": {
              "$ref": "#/components/schemas/FieldError"
            }
          }
        }
      },
      "FieldError": {
        "type": "object",
        "required": [
          "field",
          "message"
        ],
        "properties": {
          "field": {
            "type": "string",
            "example": "name"
          },
          "message": {
            "type": "string",
            "example": "must not be blank"
          }
        }
      }
    }
  }
}